apitestframework/__init__.py
apitestframework/apitestmain.py
apitestframework/test_case.py
apitestframework/test_case2.py
apitestframework/apitestbasiclib/__init__.py
apitestframework/apitestbasiclib/apibasic.py
apitestframework/apitestbasiclib/apirequest.py
apitestframework/apitestbasiclib/apitestlogic.py
apitestframework/apitestbasiclib/dbutils.py
apitestframework/apitestbasiclib/filetools.py
apitestframework/apitestbasiclib/jsoncompare.py
apitestframework/apitestbasiclib/log.py
coopapitestframework-1.3.data/scripts/apitestmain.py
yamlapitest/__init__.py
yamlapitest/apitestmain.py
yamlapitest/test_case.py
yamlapitest/test_case2.py
yamlapitest/apitestbasiclib/__init__.py
yamlapitest/apitestbasiclib/apibasic.py
yamlapitest/apitestbasiclib/apirequest.py
yamlapitest/apitestbasiclib/apitestlogic.py
yamlapitest/apitestbasiclib/dbutils.py
yamlapitest/apitestbasiclib/filetools.py
yamlapitest/apitestbasiclib/jsoncompare.py
yamlapitest/apitestbasiclib/log.py
coopapitestframework-1.3.dist-info/METADATA
coopapitestframework-1.3.dist-info/WHEEL
coopapitestframework-1.3.dist-info/entry_points.txt
coopapitestframework-1.3.dist-info/top_level.txt
coopapitestframework-1.3.dist-info/RECORD
