Metadata-Version: 2.1
Name: coopapitestframework
Version: 1.3
Summary: python接口自动化开发基础库
Home-page: UNKNOWN
Author: wu weiping
Author-email: 115773673@qq.com  
License: UNKNOWN
Keywords: django,jaeger,jaegertracing
Platform: UNKNOWN
Requires-Python: >=3.6
